{
  "objectInfo" : {
    "id" : "5Pk1Y5D2KC4i1qr5NIX8ol",
    "name" : "PullByCommitHash_Mapping - Edit",
    "type" : "DTEMPLATE",
    "metadata" : {
      "modelVersion" : {
        "major" : 0,
        "minor" : 0
      },
      "repoInfo" : {
        "repoHandle" : "0100031700000000001L"
      },
      "contextAttributes" : [ {
        "name" : "id",
        "value" : "@1"
      } ],
      "additionalInfo" : {
        "description" : "Mapping for testing Edit changes. ",
        "contentType" : "JSON",
        "documentState" : "INVALID"
      }
    }
  },
  "dataFileExtension" : "zip",
  "updateTime" : "2023-07-21T07:34:17.194Z",
  "objectRefs" : [ ]
}